README.md
setup.py
edx_downloader.egg-info/PKG-INFO
edx_downloader.egg-info/SOURCES.txt
edx_downloader.egg-info/dependency_links.txt
edx_downloader.egg-info/entry_points.txt
edx_downloader.egg-info/requires.txt
edx_downloader.egg-info/top_level.txt
edxdownloader/__init__.py
edxdownloader/__main__.py
edxdownloader/lib.py
edxdownloader/utils.py