Metadata-Version: 2.1
Name: edx-downloader
Version: 1.0.2
Summary: CLI downloader for EDX video courses. Download all course videos from https://edx.org easily.
Home-page: https://github.com/rehmatworks/edx-downloader
Author: Rehmat Alam
Author-email: contact@rehmat.works
License: MIT
Platform: UNKNOWN
